LICENSE.txt
MANIFEST.in
README.md
pyproject.toml
tox.ini
docs/code-of-conduct.md
docs/conf.py
docs/contributing.md
docs/getting-started.md
docs/index.rst
docs/plugin-module.rst
docs/requirements.txt
docs/_static/css/custom.css
src/danoan/word_def/plugins/modules/english_collins.py
src/word_def_plugin_english_collins.egg-info/PKG-INFO
src/word_def_plugin_english_collins.egg-info/SOURCES.txt
src/word_def_plugin_english_collins.egg-info/dependency_links.txt
src/word_def_plugin_english_collins.egg-info/requires.txt
src/word_def_plugin_english_collins.egg-info/top_level.txt
tests/conftest.py
tests/plugins/modules/english_collins/test_collins_api.py
tests/plugins/modules/english_collins/test_english_collins.py
tests/plugins/modules/english_collins/input/legitim.json