Metadata-Version: 2.1
Name: word-def-plugin-english-collins
Version: 0.2.0
Summary: Plugin to word-def package that connects to the English Collins dictionary
Author-email: Daniel Martins Antunes <danoan2008@gmail.com>
License: MIT License
Project-URL: Documentation, https://github.com/danoan/word-def-plugin-english-collins#readme
Project-URL: Issues, https://github.com/danoan/word-def-plugin-english-collins
Project-URL: Source, https://github.com/danoan/word-def-plugin-english-collins
Classifier: Development Status :: 4 - Beta
Classifier: Programming Language :: Python
Classifier: Programming Language :: Python :: 3.8
Classifier: Programming Language :: Python :: Implementation :: CPython
Classifier: Programming Language :: Python :: Implementation :: PyPy
Requires-Python: >=3.8
License-File: LICENSE.txt
Requires-Dist: beautifulsoup4
Requires-Dist: pycountry
Requires-Dist: toml
Requires-Dist: collins-dictionary-api-client<=1.0.0
Requires-Dist: word-def<=1.0.0
